salient/__init__.py
salient/salient.py
salient-0.1.1.dist-info/entry_points.txt
salient-0.1.1.dist-info/WHEEL
salient-0.1.1.dist-info/METADATA
salient-0.1.1.dist-info/RECORD
