Metadata-Version: 2.1
Name: salient
Version: 0.1.1
Summary: Salient: A simple SqlAlchemy Linter.
Home-page: https://github.com/TomFaulkner/sa_lint
Author: Tom Faulkner
Author-email: faulkner@pm.me
Requires-Python: >=3.8
Classifier: Programming Language :: Python :: 3
Classifier: Programming Language :: Python :: 3.8
Classifier: Programming Language :: Python :: 3.9
